l33t/__init__.py
l33t/__main__.py
l33t/version.py
l33t-0.1.0.dist-info/entry_points.txt
l33t-0.1.0.dist-info/WHEEL
l33t-0.1.0.dist-info/METADATA
l33t-0.1.0.dist-info/RECORD
